financial_analysis_project/__init__.py
financial_analysis_project/data_analysis.py
financial_analysis_project/data_navigation.py
financial_analysis_project/realtime_market_data.py
financial_analysis_project/stock_tickers.py
financial_analysis_project-0.1.0.dist-info/METADATA
financial_analysis_project-0.1.0.dist-info/WHEEL
financial_analysis_project-0.1.0.dist-info/licenses/LICENSE
financial_analysis_project-0.1.0.dist-info/RECORD
