Metadata-Version: 2.4
Name: financial_analysis_project
Version: 0.1.0
Summary: Tools for real-time market data analysis and financial modeling
Project-URL: Homepage, https://github.com/hsph-bst236/midterm-project-bytewise236
Project-URL: Issues, https://github.com/hsph-bst236/midterm-project-bytewise236/issues
Author-email: Suhwan Bong <suhwanbong@fas.harvard.edu>, Bella Qian <yqian@hsph.harvard.edu>, Yibin Xiong <yxiong@hsph.harvard.edu>
License-Expression: MIT
License-File: LICENSE
Classifier: Operating System :: OS Independent
Classifier: Programming Language :: Python :: 3
Requires-Python: >=3.7
Requires-Dist: alpha-vantage>=0.1.2
Requires-Dist: hmmlearn>=0.2.8
Requires-Dist: matplotlib>=3.4.2
Requires-Dist: networkx>=2.5.1
Requires-Dist: numpy>=1.21.0
Requires-Dist: pandas>=1.3.0
Requires-Dist: scikit-learn>=0.24.2
Requires-Dist: websocket>=0.2.1
Requires-Dist: yfinance>=0.1.63
